hook/__init__.py
hook/asg_scaling_processes.py
sceptre_aws_asg_scaling_processes_hook-1.0.1.dist-info/METADATA
sceptre_aws_asg_scaling_processes_hook-1.0.1.dist-info/WHEEL
sceptre_aws_asg_scaling_processes_hook-1.0.1.dist-info/entry_points.txt
sceptre_aws_asg_scaling_processes_hook-1.0.1.dist-info/top_level.txt
sceptre_aws_asg_scaling_processes_hook-1.0.1.dist-info/RECORD
