Metadata-Version: 2.1
Name: sceptre-aws-asg-scaling-processes-hook
Version: 1.0.1
Summary: AWS Auto Scaling Group Scaling Processes hook.
Home-page: https://github.com/sceptre/sceptre-aws-asg-scaling-processes-hook
Author: Sceptre
Author-email: sceptre@cloudreach.com
License: Apache2
Keywords: sceptre,sceptre-hook
Platform: UNKNOWN
Classifier: Intended Audience :: Developers
Classifier: Natural Language :: English
Classifier: Environment :: Console
Classifier: Programming Language :: Python :: 2.7
Classifier: Programming Language :: Python :: 3.5
Classifier: Programming Language :: Python :: 3.6
Classifier: Programming Language :: Python :: 3.7
Requires-Dist: sceptre (>=2.7)
Provides-Extra: test
Requires-Dist: pytest (>=3.2) ; extra == 'test'
